pathfinding/__init__.py
pathfinding/core/__init__.py
pathfinding/core/diagonal_movement.py
pathfinding/core/graph.py
pathfinding/core/grid.py
pathfinding/core/heap.py
pathfinding/core/heuristic.py
pathfinding/core/node.py
pathfinding/core/util.py
pathfinding/core/world.py
pathfinding/finder/__init__.py
pathfinding/finder/a_star.py
pathfinding/finder/best_first.py
pathfinding/finder/bi_a_star.py
pathfinding/finder/bi_best_first.py
pathfinding/finder/bi_breadth_first.py
pathfinding/finder/bi_dijkstra.py
pathfinding/finder/breadth_first.py
pathfinding/finder/dijkstra.py
pathfinding/finder/finder.py
pathfinding/finder/ida_star.py
pathfinding/finder/msp.py
pathfinding-1.0.20.dist-info/licenses/LICENSE
pathfinding-1.0.20.dist-info/METADATA
pathfinding-1.0.20.dist-info/WHEEL
pathfinding-1.0.20.dist-info/top_level.txt
pathfinding-1.0.20.dist-info/RECORD
