Metadata-Version: 2.4
Name: pathfinding
Version: 1.0.20
Summary: Path finding algorithms (based on Pathfinding.JS)
Home-page: https://github.com/brean/python-pathfinding
Author: Andreas Bresser
License: MIT
License-File: LICENSE
Dynamic: author
Dynamic: description
Dynamic: description-content-type
Dynamic: home-page
Dynamic: license
Dynamic: license-file
Dynamic: summary
